worden/__init__.py
worden/__main__.py
worden/const.py
worden/data/mapimg.png
worden/src/app.py
worden/src/api/api_man.py
worden/src/api/api_utils.py
worden/src/api/astronaut.py
worden/src/api/body.py
worden/src/api/event.py
worden/src/api/launch.py
worden/src/api/space_station.py
worden/src/api/trackable_object.py
worden/src/ui/list_and_details_form.py
worden/src/ui/map_form.py
worden/src/ui/ui_utils.py
worden-1.1.0.dist-info/LICENSE
worden-1.1.0.dist-info/METADATA
worden-1.1.0.dist-info/WHEEL
worden-1.1.0.dist-info/entry_points.txt
worden-1.1.0.dist-info/top_level.txt
worden-1.1.0.dist-info/RECORD
