Metadata-Version: 2.1
Name: worden
Version: 1.1.0
Summary: TUI Space operations center
Home-page: https://github.com/jvlsg/Worden
Author: João Guimarães
Author-email: jvlsg-github@ipriva.org
License: UNKNOWN
Platform: UNKNOWN
Classifier: Programming Language :: Python :: 3
Classifier: License :: OSI Approved :: MIT License
Classifier: Operating System :: OS Independent
Classifier: Environment :: Console :: Curses
Classifier: Intended Audience :: Education
Classifier: Natural Language :: English
Requires-Python: >=3.7
Requires-Dist: Pillow (>=5.4.1)
Requires-Dist: drawille (>=0.1.0)
Requires-Dist: npyscreen (>=4.10.5)
